autojenkins/__init__.py
autojenkins/jobs.py
autojenkins/run.py
autojenkins-1.1.1.dist-info/DESCRIPTION.rst
autojenkins-1.1.1.dist-info/METADATA
autojenkins-1.1.1.dist-info/RECORD
autojenkins-1.1.1.dist-info/WHEEL
autojenkins-1.1.1.dist-info/entry_points.txt
autojenkins-1.1.1.dist-info/metadata.json
autojenkins-1.1.1.dist-info/top_level.txt
