Metadata-Version: 2.0
Name: autojenkins
Version: 1.1.1
Summary: Jenkins Remote Control Library
Home-page: https://github.com/txels/autojenkins
Author: Carles Barrobés
Author-email: carles@barrobes.com
License: UNKNOWN
Platform: UNKNOWN
Classifier: Development Status :: 4 - Beta
Classifier: Environment :: Console
Classifier: Intended Audience :: Developers
Classifier: Intended Audience :: System Administrators
Classifier: License :: OSI Approved :: GNU Library or Lesser General Public License (LGPL)
Classifier: Operating System :: OS Independent
Classifier: Programming Language :: Python
Classifier: Topic :: Software Development :: Build Tools
Classifier: Topic :: Software Development :: Libraries
Requires-Dist: docopt
Requires-Dist: jinja2
Requires-Dist: requests
